agentils/__init__.py
agentils/main.py
agentils/utils.py
agentils-0.1.0.dist-info/METADATA
agentils-0.1.0.dist-info/WHEEL
agentils-0.1.0.dist-info/entry_points.txt
agentils-0.1.0.dist-info/licenses/LICENSE
agentils-0.1.0.dist-info/RECORD
