Metadata-Version: 2.4
Name: agentils
Version: 0.1.0
Summary: AI Agent Utilities - Powerful toolkit for building AI agents with LLM integration and decorators
Project-URL: Homepage, https://github.com/aggreyeric/agentils
Project-URL: Repository, https://github.com/aggreyeric/agentils
Project-URL: Documentation, https://github.com/aggreyeric/agentils#readme
Project-URL: Issues, https://github.com/aggreyeric/agentils/issues
Author-email: aggreyeric <ericaggrey@outlook.com>
License: MIT
License-File: LICENSE
Keywords: agents,ai,decorators,gemini,llm,utilities
Classifier: Development Status :: 3 - Alpha
Classifier: Intended Audience :: Developers
Classifier: License :: OSI Approved :: MIT License
Classifier: Programming Language :: Python :: 3
Classifier: Programming Language :: Python :: 3.9
Classifier: Programming Language :: Python :: 3.10
Classifier: Programming Language :: Python :: 3.11
Classifier: Programming Language :: Python :: 3.12
Classifier: Topic :: Scientific/Engineering :: Artificial Intelligence
Classifier: Topic :: Software Development :: Libraries :: Python Modules
Requires-Python: >=3.9
Requires-Dist: google-genai>=0.3.0
Requires-Dist: pydantic>=2.11.7
Provides-Extra: dev
Requires-Dist: black>=22.0.0; extra == 'dev'
Requires-Dist: isort>=5.0.0; extra == 'dev'
Requires-Dist: mypy>=1.0.0; extra == 'dev'
Requires-Dist: pre-commit>=2.0.0; extra == 'dev'
Requires-Dist: pytest>=7.0.0; extra == 'dev'
